pylsh0219/__init__.py
pylsh0219/compare_excel.py
pylsh0219/config.json
pylsh0219/filter_rules.json
pylsh0219/get_gift_1.py
pylsh0219/gift_records.py
pylsh0219/main_event_chrome.py
pylsh0219/ocr_gift_content_new.py
pylsh0219/select_games.py
pylsh0219-0.1.0.dist-info/METADATA
pylsh0219-0.1.0.dist-info/WHEEL
pylsh0219-0.1.0.dist-info/RECORD
