Metadata-Version: 2.3
Name: pylsh0219
Version: 0.1.0
Summary: 
Author: ChaoZhi Zhang
Author-email: xiaozhizhang777@gmail.com
Requires-Python: >=3.13
Classifier: Programming Language :: Python :: 3
Classifier: Programming Language :: Python :: 3.13
Requires-Dist: lxml (>=5.3.1,<6.0.0)
Requires-Dist: openpyxl (>=3.1.5,<4.0.0)
Requires-Dist: paddleocr (>=2.9.1,<3.0.0)
Requires-Dist: pandas (>=2.2.3,<3.0.0)
Requires-Dist: requests (>=2.32.3,<3.0.0)
Requires-Dist: selenium (>=4.28.1,<5.0.0)
